natcap/__init__.py
natcap/opal/__init__.py
natcap/opal/adept_core.py
natcap/opal/analysis.py
natcap/opal/offsets.py
natcap/opal/preprocessing.py
natcap/opal/reporting.py
natcap/opal/static_maps.py
natcap/opal/utils.py
natcap/opal/version.py
natcap/opal/i18n/__init__.py
natcap/opal/i18n/msgfmt.py
natcap/opal/report_data/jquery-1.11.3.min.js
natcap/opal/report_data/permitting_functions.js
natcap/opal/report_data/qunit-1.19.0.css
natcap/opal/report_data/qunit-1.19.0.js
natcap/opal/report_data/table_row_mouseover.js
natcap/opal/report_data/table_style.css
natcap/opal/report_data/tests.html
natcap/opal/report_data/tests.js
natcap/opal/report_data/toc.min.js
natcap/opal/static_data/carbon_parameters.json
natcap/opal/static_data/common_data.json
natcap/opal/static_data/nutrient_parameters.json
natcap/opal/static_data/sdr_parameters.json
natcap/opal/tests/__init__.py
natcap/opal/tests/test_offsets.py
natcap/opal/tests/test_preprocessing.py
natcap/opal/tests/test_reporting.py
natcap/opal/tests/test_smoke.py
natcap/opal/tests/test_static_maps.py
natcap/opal/tests/test_testing.py
natcap/opal/tests/test_utils.py
natcap.opal-1.1.0.dist-info/DESCRIPTION.rst
natcap.opal-1.1.0.dist-info/METADATA
natcap.opal-1.1.0.dist-info/metadata.json
natcap.opal-1.1.0.dist-info/RECORD
natcap.opal-1.1.0.dist-info/top_level.txt
natcap.opal-1.1.0.dist-info/WHEEL
