Metadata-Version: 2.0
Name: natcap.opal
Version: 1.1.0
Summary: Decision support tool for mitigating development impacts to ecosystem services
Home-page: https://bitbucket.org/natcap/opal
Author: James Douglass
Author-email: jdouglass@stanford.edu
License: This tool has an open license. All people are invited to use the tool
